classes/tools.py
science_museum_mcp/__init__.py
science_museum_mcp/__main__.py
science_museum_mcp/constants.py
science_museum_mcp/science_museum_api.py
science_museum_mcp/server.py
science_museum_mcp-1.0.0.dist-info/licenses/LICENSE.md
science_museum_mcp-1.0.0.dist-info/METADATA
science_museum_mcp-1.0.0.dist-info/WHEEL
science_museum_mcp-1.0.0.dist-info/entry_points.txt
science_museum_mcp-1.0.0.dist-info/top_level.txt
science_museum_mcp-1.0.0.dist-info/RECORD
