Metadata-Version: 2.4
Name: science-museum-mcp
Version: 1.0.0
Summary: MCP Server for the British Science Museum
Requires-Python: >=3.13
License-File: LICENSE.md
Requires-Dist: mcp[cli]>=1.4.1
Requires-Dist: pytest>=8.3.5
Requires-Dist: requests>=2.32.3
Dynamic: license-file
